CHANGELOG.txt
LICENSE.txt
MANIFEST.in
Makefile
README.md
qt_designer.ui
setup.py
obspyck/__init__.py
obspyck/event_helper.py
obspyck/example.cfg
obspyck/obspyck.gif
obspyck/obspyck.py
obspyck/obspyck_16x16.gif
obspyck/obspyck_24x24.gif
obspyck/obspyck_32x32.gif
obspyck/obspyck_48x48.gif
obspyck/qt_designer.py
obspyck/rotate_to_zne.py
obspyck/util.py
obspyck.egg-info/PKG-INFO
obspyck.egg-info/SOURCES.txt
obspyck.egg-info/dependency_links.txt
obspyck.egg-info/entry_points.txt
obspyck.egg-info/requires.txt
obspyck.egg-info/top_level.txt