Metadata-Version: 1.1
Name: obspyck
Version: 0.8.0
Summary: A GUI application for seismogram analysis
Home-page: https://github.com/megies/obspyck
Author: Tobias Megies
Author-email: megies@geophysik.uni-muenchen.de
License: UNKNOWN
Download-URL: https://github.com/megies/obspyck.git
Keywords: obspy,github,seismology,earthquake,seismogram
Platform: UNKNOWN
Classifier: Programming Language :: Python
Classifier: Development Status :: 4 - Beta
Classifier: Intended Audience :: Developers
Classifier: License :: OSI Approved :: GNU General Public License v3 (GPLv3)
Classifier: Operating System :: OS Independent
Classifier: Programming Language :: Python
Classifier: Programming Language :: Python :: 3
Classifier: Programming Language :: Python :: 3.7
Classifier: Topic :: Software Development :: Libraries :: Python Modules
